kodi_json-1.0.0.dist-info/WHEEL
kodi_json-1.0.0.dist-info/top_level.txt
kodi_json-1.0.0.dist-info/METADATA
kodi_json-1.0.0.dist-info/metadata.json
kodi_json-1.0.0.dist-info/RECORD
kodi_json-1.0.0.dist-info/DESCRIPTION.rst
kodijson/__init__.py
kodijson/kodijson.py
